featurevis/__init__.py
featurevis/core.py
featurevis/exceptions.py
featurevis/models.py
featurevis/ops.py
featurevis/utils.py
laminr/__init__.py
laminr/contrastive_loss.py
laminr/coordinate_transforms.py
laminr/inr.py
laminr/inv_temp_learn_match.py
laminr/neuron_models/__init__.py
laminr/neuron_models/monkey_models.py
laminr/neuron_models/simulated_models.py
laminr/neuron_models/utils/__init__.py
laminr/neuron_models/utils/monkey_model.py
laminr/neuron_models/utils/simulated_model.py
laminr/utils/__init__.py
laminr/utils/general.py
laminr/utils/img_similarity_metrics.py
laminr/utils/img_transforms.py
laminr/utils/mask.py
laminr/utils/mei.py
laminr/utils/training.py
neuralpredictors/__init__.py
neuralpredictors/distributions.py
neuralpredictors/regularizers.py
neuralpredictors/utils.py
neuralpredictors/data/__init__.py
neuralpredictors/data/exceptions.py
neuralpredictors/data/samplers.py
neuralpredictors/data/transforms.py
neuralpredictors/data/utils.py
neuralpredictors/data/datasets/__init__.py
neuralpredictors/data/datasets/base.py
neuralpredictors/data/datasets/movies.py
neuralpredictors/data/datasets/old_datasets.py
neuralpredictors/data/datasets/statics/__init__.py
neuralpredictors/data/datasets/statics/base.py
neuralpredictors/data/datasets/statics/filetree.py
neuralpredictors/layers/__init__.py
neuralpredictors/layers/activations.py
neuralpredictors/layers/affine.py
neuralpredictors/layers/attention.py
neuralpredictors/layers/conv.py
neuralpredictors/layers/hermite.py
neuralpredictors/layers/squeeze_excitation.py
neuralpredictors/layers/cores/__init__.py
neuralpredictors/layers/cores/base.py
neuralpredictors/layers/cores/conv2d.py
neuralpredictors/layers/encoders/__init__.py
neuralpredictors/layers/encoders/firing_rate.py
neuralpredictors/layers/modulators/__init__.py
neuralpredictors/layers/readouts/__init__.py
neuralpredictors/layers/readouts/attention.py
neuralpredictors/layers/readouts/base.py
neuralpredictors/layers/readouts/factorized.py
laminr-0.0.7.dist-info/LICENSE.md
laminr-0.0.7.dist-info/METADATA
laminr-0.0.7.dist-info/WHEEL
laminr-0.0.7.dist-info/top_level.txt
laminr-0.0.7.dist-info/RECORD
