Metadata-Version: 2.2
Name: laminr
Version: 0.0.7
Summary: Learning and Aligning Manifolds using Implicit Neural Representations.
Author-email: Mohammad Bashiri <mohammadbashiri93@gmail.com>, Luca Baroni <loocabaroni@gmail.com>
Project-URL: Homepage, https://github.com/sinzlab/laminr
Project-URL: Repository, https://github.com/sinzlab/laminr
Project-URL: Documentation, https://github.com/sinzlab/laminr
Project-URL: Issues, https://github.com/sinzlab/laminr/issues
Requires-Python: >=3.9
License-File: LICENSE.md
Requires-Dist: tqdm
Requires-Dist: torch>=1.13.1
Requires-Dist: torchvision
Requires-Dist: numpy>=1.21
Requires-Dist: huggingface_hub>=0.28.1
Requires-Dist: scikit-image>=0.19.1
Requires-Dist: scipy>=1.7
Requires-Dist: lipstick>=0.0.7
Requires-Dist: matplotlib>=3.4.3
Provides-Extra: colab
Requires-Dist: lipstick>=0.0.7; extra == "colab"
